fandogh_cli/__init__.py
fandogh_cli/base_commands.py
fandogh_cli/config.py
fandogh_cli/domain_commands.py
fandogh_cli/exec_commands.py
fandogh_cli/fandogh.py
fandogh_cli/image_commands.py
fandogh_cli/info_collector.py
fandogh_cli/managed_service_commands.py
fandogh_cli/namespace_commands.py
fandogh_cli/presenter.py
fandogh_cli/secret_commands.py
fandogh_cli/service_commands.py
fandogh_cli/utils.py
fandogh_cli/version_check.py
fandogh_cli/volume_commands.py
fandogh_cli/workspace.py
fandogh_cli/fandogh_client/__init__.py
fandogh_cli/fandogh_client/domain_client.py
fandogh_cli/fandogh_client/error_report_client.py
fandogh_cli/fandogh_client/exec_client.py
fandogh_cli/fandogh_client/namespace_client.py
fandogh_cli/fandogh_client/secrets_client.py
fandogh_cli/presenter/__init__.py
fandogh_cli/presenter/base_presenter.py
fandogh_cli/presenter/service_presenter.py
fandogh_cli-1.0.1.dist-info/METADATA
fandogh_cli-1.0.1.dist-info/RECORD
fandogh_cli-1.0.1.dist-info/WHEEL
fandogh_cli-1.0.1.dist-info/entry_points.txt
fandogh_cli-1.0.1.dist-info/top_level.txt
