Metadata-Version: 2.1
Name: fandogh-cli
Version: 1.0.1
Summary: Official CLI for Fandogh PaaS
Home-page: https://github.com/fandoghpaas/fandogh-cli
Author: Soroosh Sarabadani
Author-email: soroosh.sarabadani@gmail.com
License: UNKNOWN
Keywords: PaaS,Fandogh
Platform: UNKNOWN
Classifier: Development Status :: 5 - Production/Stable
Classifier: Topic :: Utilities
Classifier: License :: OSI Approved :: BSD License
Requires-Dist: click
Requires-Dist: pyOpenSSL
Requires-Dist: requests[security]
Requires-Dist: requests-toolbelt
Requires-Dist: beautifultable
Requires-Dist: pytz
Requires-Dist: tzlocal
Requires-Dist: pyyaml
